aeropress/__init__.py
aeropress/_version.py
aeropress/cli.py
aeropress/aws/__init__.py
aeropress/aws/alarm.py
aeropress/aws/cluster.py
aeropress/aws/log.py
aeropress/aws/metric.py
aeropress/aws/scale.py
aeropress/aws/service.py
aeropress/aws/task.py
aeropress-0.0.31.dist-info/METADATA
aeropress-0.0.31.dist-info/WHEEL
aeropress-0.0.31.dist-info/entry_points.txt
aeropress-0.0.31.dist-info/top_level.txt
aeropress-0.0.31.dist-info/RECORD
