Metadata-Version: 2.1
Name: aeropress
Version: 0.0.31
Summary: Helper for deploying Docker images to AWS ECS.
Home-page: https://github.com/muraty/aeropress
Author: Omer Murat Yildirim
Author-email: omermuratyildirim@gmail.com
License: BSD License
Keywords: aws ecs deploy aeropress docker image container containerization
Platform: UNKNOWN
Requires-Python: >=3.5.2
Requires-Dist: boto3 (>=1.9)
